cima/goes/products.py
cima/goes/aio/gcs/__init__.py
cima/goes/aio/gcs/blobs.py
cima/goes/aio/gcs/gcs.py
cima/goes/aio/tasks_store/__init__.py
cima/goes/aio/tasks_store/commands.py
cima/goes/aio/tasks_store/singleton.py
cima/goes/aio/tasks_store/store.py
cima/goes/datasets/__init__.py
cima/goes/datasets/clipping.py
cima/goes/examples/SA_project/download_all_ir.py
cima/goes/examples/SA_project/download_relampago_ir.py
cima/goes/examples/SA_project/download_relampago_vis.py
cima/goes/examples/SA_project/generate_info_files.py
cima/goes/examples/SA_project/generate_one_file.py
cima/goes/examples/SA_project/initialize_database_all_ir.py
cima/goes/examples/SA_project/initialize_database_relampago_ir.py
cima/goes/examples/SA_project/initialize_database_relampago_vis.py
cima_goes_aio-0.1b12.data/data/LICENSE
cima_goes_aio-0.1b12.dist-info/LICENSE
cima_goes_aio-0.1b12.dist-info/METADATA
cima_goes_aio-0.1b12.dist-info/WHEEL
cima_goes_aio-0.1b12.dist-info/top_level.txt
cima_goes_aio-0.1b12.dist-info/RECORD
