Metadata-Version: 2.1
Name: cima-goes-aio
Version: 0.1b12
Summary: GOES-16 File Processing with asyncio and multiprocessing
Home-page: https://github.com/garciafido/cima-goes-aio
Author: Fido Garcia
Author-email: garciafido@gmail.com
License: MIT
Classifier: Programming Language :: Python :: 3
Classifier: License :: OSI Approved :: MIT License
Classifier: Operating System :: OS Independent
Requires-Python: >=3.12
License-File: LICENSE
